{"singlePage": [], "startSite": "", "filingNum": "", "onePageListNum": 15, "commentLabelColor": "#006b75", "yearColorList": ["#bc4c00", "#0969da", "#1f883d", "#A333D0"], "i18n": "CN", "themeMode": "manual", "dayTheme": "light", "nightTheme": "dark", "urlMode": "pinyin", "script": "", "style": "", "head": "", "indexScript": "", "indexStyle": "", "bottomText": "", "showPostSource": 1, "iconList": {}, "UTC": 8, "rssSplit": "sentence", "exlink": {}, "needComment": 1, "allHead": "", "title": "\u7b80\u8a00\u306e\u535a\u5ba2", "subTitle": "Blog description", "avatarUrl": "https://github.githubassets.com/favicons/favicon.svg", "GMEEK_VERSION": "last", "postListJson": {"P5": {"htmlDir": "docs/post/SDFGFGSD.html", "labels": ["documentation"], "postTitle": "SDFGFGSD", "postUrl": "post/SDFGFGSD.html", "postSourceUrl": "https://github.com/mrfang-xi/mrfang-xi.github.io/issues/5", "commentNum": 0, "wordCount": 160, "description": "**FASDSDFGASDG**\r\n### _ASGASDGSD_\r\nASFDAS\r\n\r\n![\u5c0f\u72d7 \u5c0f\u53ef\u7231 \u6d77\u8fb9 4k\u58c1\u7eb8 3840x2400_\u5f7c\u5cb8\u56fe\u7f51](https://github.com/user-attachments/assets/439edc06-6021-48ad-95de-67b0c7859a99)\r\n\u3002", "top": 0, "createdAt": 1720782892, "style": "", "script": "", "head": "", "ogImage": "https://github.githubassets.com/favicons/favicon.svg", "createdDate": "2024-07-12", "dateLabelColor": "#bc4c00"}, "P6": {"htmlDir": "docs/post/TRDTRTY.html", "labels": ["documentation"], "postTitle": "TRDTRTY", "postUrl": "post/TRDTRTY.html", "postSourceUrl": "https://github.com/mrfang-xi/mrfang-xi.github.io/issues/6", "commentNum": 0, "wordCount": 26, "description": "SDFHGRSHSH\r\nSHFGSGFSSSSFGH\u3002", "top": 0, "createdAt": 1720782951, "style": "", "script": "", "head": "", "ogImage": "https://github.githubassets.com/favicons/favicon.svg", "createdDate": "2024-07-12", "dateLabelColor": "#bc4c00"}}, "singeListJson": {}, "labelColorDict": {"bug": "#d73a4a", "documentation": "#0075ca", "duplicate": "#cfd3d7", "enhancement": "#a2eeef", "good first issue": "#7057ff", "help wanted": "#008672", "invalid": "#e4e669", "question": "#d876e3", "wontfix": "#ffffff"}, "displayTitle": "\u7b80\u8a00\u306e\u535a\u5ba2", "faviconUrl": "https://github.githubassets.com/favicons/favicon.svg", "ogImage": "https://github.githubassets.com/favicons/favicon.svg", "primerCSS": "<link href='https://mirrors.sustech.edu.cn/cdnjs/ajax/libs/Primer/21.0.7/primer.css' rel='stylesheet' />", "homeUrl": "https://mrfang-xi.github.io", "prevUrl": "disabled", "nextUrl": "disabled"}